JianZhiQianduanOfferFix1/README.md
JianZhiQianduanOfferFix1/__init__.py
JianZhiQianduanOfferFix1/__main__.py
JianZhiQianduanOfferFix1/file.epub
JianZhiQianduanOfferFix1/index.html
JianZhiQianduanOfferFix1/css/__init__.py
JianZhiQianduanOfferFix1/css/annotations.css
JianZhiQianduanOfferFix1/css/main.css
JianZhiQianduanOfferFix1/css/normalize.css
JianZhiQianduanOfferFix1/css/popup.css
JianZhiQianduanOfferFix1/font/__init__.py
JianZhiQianduanOfferFix1/font/fontello.eot
JianZhiQianduanOfferFix1/font/fontello.svg
JianZhiQianduanOfferFix1/font/fontello.ttf
JianZhiQianduanOfferFix1/font/fontello.woff
JianZhiQianduanOfferFix1/img/__init__.py
JianZhiQianduanOfferFix1/img/annotator-glyph-sprite.png
JianZhiQianduanOfferFix1/img/annotator-icon-sprite.png
JianZhiQianduanOfferFix1/img/apple-touch-icon.png
JianZhiQianduanOfferFix1/img/cancelfullscreen.png
JianZhiQianduanOfferFix1/img/close.png
JianZhiQianduanOfferFix1/img/fullscreen.png
JianZhiQianduanOfferFix1/img/loader.gif
JianZhiQianduanOfferFix1/img/menu-icon.png
JianZhiQianduanOfferFix1/img/save.png
JianZhiQianduanOfferFix1/img/saved.png
JianZhiQianduanOfferFix1/img/settings-s.png
JianZhiQianduanOfferFix1/img/settings.png
JianZhiQianduanOfferFix1/img/star.png
JianZhiQianduanOfferFix1/js/__init__.py
JianZhiQianduanOfferFix1/js/epub.js
JianZhiQianduanOfferFix1/js/epub.min.js
JianZhiQianduanOfferFix1/js/epub.min.map
JianZhiQianduanOfferFix1/js/hooks.min.js
JianZhiQianduanOfferFix1/js/hooks.min.map
JianZhiQianduanOfferFix1/js/reader.js
JianZhiQianduanOfferFix1/js/reader.js.map
JianZhiQianduanOfferFix1/js/reader.min.js
JianZhiQianduanOfferFix1/js/reader.min.map
JianZhiQianduanOfferFix1/js/hooks/__init__.py
JianZhiQianduanOfferFix1/js/hooks/extensions/__init__.py
JianZhiQianduanOfferFix1/js/hooks/extensions/highlight.js
JianZhiQianduanOfferFix1/js/libs/__init__.py
JianZhiQianduanOfferFix1/js/libs/jquery.min.js
JianZhiQianduanOfferFix1/js/libs/localforage.min.js
JianZhiQianduanOfferFix1/js/libs/screenfull.js
jian_zhi_qianduan_offer_fix1-2025.3.25.1.dist-info/METADATA
jian_zhi_qianduan_offer_fix1-2025.3.25.1.dist-info/WHEEL
jian_zhi_qianduan_offer_fix1-2025.3.25.1.dist-info/entry_points.txt
jian_zhi_qianduan_offer_fix1-2025.3.25.1.dist-info/top_level.txt
jian_zhi_qianduan_offer_fix1-2025.3.25.1.dist-info/RECORD
